Metadata-Version: 1.0
Name: ruthviknewcal
Version: 0.0.1
Summary: this is a trial package used for calculation.
Home-page: UNKNOWN
Author: Ruthvik RK
Author-email: ruthvikrk162@gmail.com
License: MIT
Platform: UNKNOWN
